ezsave_shayanvd/__init__.py
ezsave_shayanvd/ezsave.py
ezsave_shayanvd-0.0.2.dist-info/METADATA
ezsave_shayanvd-0.0.2.dist-info/WHEEL
ezsave_shayanvd-0.0.2.dist-info/licenses/LICENSE
ezsave_shayanvd-0.0.2.dist-info/RECORD
